project_func/__init__.py
project_func/cli.py
project_func/engine.py
project_func/scripts/__init__.py
project_func/scripts/database.py
project_func/scripts/main_base.py
project_makarov_b24_505-0.1.0.dist-info/METADATA
project_makarov_b24_505-0.1.0.dist-info/WHEEL
project_makarov_b24_505-0.1.0.dist-info/entry_points.txt
project_makarov_b24_505-0.1.0.dist-info/RECORD
